[
  {
    "topic_id": "1",
    "brand": "エレクトロン",
    "product_name": "タイトニングミストブライト",
    "price": "5,940",
    "points": "1,080",
    "is_kara": "",
    "url": "https://web.hh-online.jp/hankyu-beauty/goods/index.html?ggcd=B2430426",
    "img_folder": "260508",
    "img_name": "point20_item-01-01.png",
    "attention": ""
  },
  {
    "topic_id": "1",
    "brand": "アスレティア",
    "product_name": "スキンプロテクション UVジェル C",
    "price": "4,400",
    "points": "800",
    "is_kara": "",
    "url": "https://web.hh-online.jp/hankyu-beauty/goods/index.html?ggcd=B2520191",
    "img_folder": "260508",
    "img_name": "point20_item-01-02.png",
    "attention": ""
  },
  {
    "topic_id": "1",
    "brand": "THREE",
    "product_name": "バランシング バリア ブライトニング セラム[医薬部外品]",
    "price": "12,100",
    "points": "2,200",
    "is_kara": "",
    "url": "https://web.hh-online.jp/hankyu-beauty/goods/index.html?ggcd=B2610006",
    "img_folder": "260508",
    "img_name": "point20_item-01-03.png",
    "attention": ""
  },
  {
    "topic_id": "1",
    "brand": "ロクシタン",
    "product_name": "レーヌデプレ イルミネイティングクレンジングフォーム 150ml",
    "price": "4,950",
    "points": "900",
    "is_kara": "",
    "url": "https://web.hh-online.jp/hankyu-beauty/goods/index.html?ggcd=B2530375",
    "img_folder": "260508",
    "img_name": "point20_item-01-04.png",
    "attention": ""
  },
  {
    "topic_id": "1",
    "brand": "イプサ",
    "product_name": "ブライトニングセラム［医薬部外品］",
    "price": "7,260",
    "points": "1,320",
    "is_kara": "TRUE",
    "url": "https://web.hh-online.jp/hankyu-beauty/goods/index.html?ggcd=B2350241",
    "img_folder": "260508",
    "img_name": "point20_item-01-05.png",
    "attention": ""
  },
  {
    "topic_id": "1",
    "brand": "ちふれ",
    "product_name": "美白化粧水 TA［医薬部外品］",
    "price": "770",
    "points": "140",
    "is_kara": "TRUE",
    "url": "https://web.hh-online.jp/hankyu-beauty/goods/index.html?ggcd=B2360217",
    "img_folder": "260508",
    "img_name": "point20_item-01-06.png",
    "attention": ""
  },
  {
    "topic_id": "1",
    "brand": "エスト",
    "product_name": "ブライトニング エステ[医薬部外品]",
    "price": "8,800",
    "points": "1,600",
    "is_kara": "",
    "url": "https://web.hh-online.jp/hankyu-beauty/goods/index.html?ggcd=B2510142",
    "img_folder": "260508",
    "img_name": "point20_item-01-07.png",
    "attention": ""
  },
  {
    "topic_id": "1",
    "brand": "SK-II",
    "product_name": "ジェノプティクス インフィニットオーラ エッセンス[販売名：SK-II 薬用美白美容液ST][医薬部外品]",
    "price": "22,000",
    "points": "4,000",
    "is_kara": "TRUE",
    "url": "https://web.hh-online.jp/hankyu-beauty/goods/index.html?ggcd=B2510205",
    "img_folder": "260508",
    "img_name": "point20_item-01-08.png",
    "attention": ""
  },
  {
    "topic_id": "1",
    "brand": "キールズ",
    "product_name": "DS クリアリーブライト エッセンス[販売名：キールズ DS クリアリーブライト エッセンス][医薬部外品]",
    "price": "9,460",
    "points": "1,720",
    "is_kara": "TRUE",
    "url": "https://web.hh-online.jp/hankyu-beauty/goods/index.html?ggcd=B327014",
    "img_folder": "260508",
    "img_name": "point20_item-01-09.png",
    "attention": ""
  },
  {
    "topic_id": "1",
    "brand": "RMK",
    "product_name": "インテンシブ ブライトニング ローション[医薬部外品]",
    "price": "4,400",
    "points": "800",
    "is_kara": "",
    "url": "https://web.hh-online.jp/hankyu-beauty/goods/index.html?ggcd=B2420004",
    "img_folder": "260508",
    "img_name": "point20_item-01-10.png",
    "attention": ""
  },
  {
    "topic_id": "1",
    "brand": "エピステーム",
    "product_name": "ブライトプラズムレーザー［販売名：エピステーム ブライトPL］[医薬部外品]",
    "price": "14,300",
    "points": "2,600",
    "is_kara": "",
    "url": "https://web.hh-online.jp/hankyu-beauty/goods/index.html?ggcd=B2440064",
    "img_folder": "260508",
    "img_name": "point20_item-01-11.png",
    "attention": ""
  },
  {
    "topic_id": "1",
    "brand": "ファス",
    "product_name": "FAS ザ ブラック ブライトセラム II[販売名：FBブライトセラムII][医薬部外品]",
    "price": "12,100",
    "points": "2,200",
    "is_kara": "",
    "url": "https://web.hh-online.jp/hankyu-beauty/goods/index.html?ggcd=B2610080",
    "img_folder": "260508",
    "img_name": "point20_item-01-12.png",
    "attention": ""
  },
  {
    "topic_id": "1",
    "brand": "クリニーク",
    "product_name": "イーブン ベター アクティブ ブースター セラム[医薬部外品]",
    "price": "7,810",
    "points": "1,420",
    "is_kara": "",
    "url": "https://web.hh-online.jp/hankyu-beauty/goods/index.html?ggcd=B2610046",
    "img_folder": "260508",
    "img_name": "point20_item-01-13.png",
    "attention": ""
  },
  {
    "topic_id": "2",
    "brand": "カネボウ",
    "product_name": "ヴェイル オブ デイ",
    "price": "5,500",
    "points": "1,000",
    "is_kara": "",
    "url": "https://web.hh-online.jp/hankyu-beauty/goods/index.html?ggcd=B21D0078",
    "img_folder": "260508",
    "img_name": "point20_item-02-01.png",
    "attention": ""
  },
  {
    "topic_id": "2",
    "brand": "カネボウ",
    "product_name": "グローバル スキン プロテクターa",
    "price": "5,500",
    "points": "1,000",
    "is_kara": "",
    "url": "https://web.hh-online.jp/hankyu-beauty/goods/index.html?ggcd=B2110169",
    "img_folder": "260508",
    "img_name": "point20_item-02-02.png",
    "attention": ""
  },
  {
    "topic_id": "2",
    "brand": "AHRES",
    "product_name": "ハイドレクター UVマスク",
    "price": "4,620",
    "points": "840",
    "is_kara": "",
    "url": "https://web.hh-online.jp/hankyu-beauty/goods/index.html?ggcd=B2380214",
    "img_folder": "260508",
    "img_name": "point20_item-02-03.png",
    "attention": ""
  },
  {
    "topic_id": "2",
    "brand": "オブ･コスメティックス",
    "product_name": "UVモイストエッセンス・31",
    "price": "3,300",
    "points": "600",
    "is_kara": "",
    "url": "https://web.hh-online.jp/hankyu-beauty/goods/index.html?ggcd=B2240054",
    "img_folder": "260508",
    "img_name": "point20_item-02-04.png",
    "attention": ""
  },
  {
    "topic_id": "2",
    "brand": "ランコム",
    "product_name": "アプソリュ ザ UVクリーム",
    "price": "9,900",
    "points": "1,800",
    "is_kara": "TRUE",
    "url": "https://web.hh-online.jp/hankyu-beauty/goods/index.html?ggcd=B2620012",
    "img_folder": "260508",
    "img_name": "point20_item-02-05.png",
    "attention": ""
  },
  {
    "topic_id": "2",
    "brand": "センサイ",
    "product_name": "SB プロテクティブサンケアクリーム フォーフェイス 50+",
    "price": "11,550",
    "points": "2,100",
    "is_kara": "",
    "url": "https://web.hh-online.jp/hankyu-beauty/goods/index.html?ggcd=B2420010",
    "img_folder": "260508",
    "img_name": "point20_item-02-06.png",
    "attention": ""
  },
  {
    "topic_id": "2",
    "brand": "RMK",
    "product_name": "UVフェイスプロテクター エンハンスト",
    "price": "3,850",
    "points": "700",
    "is_kara": "",
    "url": "https://web.hh-online.jp/hankyu-beauty/goods/index.html?ggcd=B2510027",
    "img_folder": "260508",
    "img_name": "point20_item-02-07.png",
    "attention": ""
  },
  {
    "topic_id": "2",
    "brand": "ファス",
    "product_name": "FAS ザ ブラック デイ クリーム[販売名：FDクリーム][医薬部外品]",
    "price": "6,600",
    "points": "1,200",
    "is_kara": "",
    "url": "https://web.hh-online.jp/hankyu-beauty/goods/index.html?ggcd=B2510072",
    "img_folder": "260508",
    "img_name": "point20_item-02-08.png",
    "attention": ""
  },
  {
    "topic_id": "2",
    "brand": "SK-II",
    "product_name": "ジェノプティクス CC プライマー",
    "price": "9,900",
    "points": "1,800",
    "is_kara": "",
    "url": "https://web.hh-online.jp/hankyu-beauty/goods/index.html?ggcd=B2530384",
    "img_folder": "260508",
    "img_name": "point20_item-02-09.png",
    "attention": ""
  },
  {
    "topic_id": "2",
    "brand": "ポール ＆ ジョー",
    "product_name": "プロテクティング プライマー",
    "price": "4,070",
    "points": "740",
    "is_kara": "",
    "url": "https://web.hh-online.jp/hankyu-beauty/goods/index.html?ggcd=B2510187",
    "img_folder": "260508",
    "img_name": "point20_item-02-10.png",
    "attention": ""
  },
  {
    "topic_id": "2",
    "brand": "アスレティア",
    "product_name": "スキンプロテクション UVジェル",
    "price": "5,500",
    "points": "1,000",
    "is_kara": "",
    "url": "https://web.hh-online.jp/hankyu-beauty/goods/index.html?ggcd=B2620041",
    "img_folder": "260508",
    "img_name": "point20_item-02-11.png",
    "attention": ""
  },
  {
    "topic_id": "2",
    "brand": "THREE",
    "product_name": "バランシング プロテクティブ UV クリーム",
    "price": "4,620",
    "points": "840",
    "is_kara": "",
    "url": "https://web.hh-online.jp/hankyu-beauty/goods/index.html?ggcd=B2520092",
    "img_folder": "260508",
    "img_name": "point20_item-02-12.png",
    "attention": ""
  },
  {
    "topic_id": "2",
    "brand": "エムアイエムシー",
    "product_name": "ミネラルミルキーUVプロテクト",
    "price": "5,500",
    "points": "1,000",
    "is_kara": "",
    "url": "https://web.hh-online.jp/hankyu-beauty/goods/index.html?ggcd=B2530056",
    "img_folder": "260508",
    "img_name": "point20_item-02-13.png",
    "attention": ""
  },
  {
    "topic_id": "2",
    "brand": "イプサ",
    "product_name": "プロテクターマルチシールド",
    "price": "4,950",
    "points": "900",
    "is_kara": "",
    "url": "https://web.hh-online.jp/hankyu-beauty/goods/index.html?ggcd=B2350237",
    "img_folder": "260508",
    "img_name": "point20_item-03-04.png",
    "attention": ""
  },
  {
    "topic_id": "3",
    "brand": "カネボウ",
    "product_name": "ジェネレイティング エッセンシャルズ",
    "price": "12,650",
    "points": "2300",
    "is_kara": "TRUE",
    "url": "https://web.hh-online.jp/hankyu-beauty/goods/index.html?ggcd=B25O0372",
    "img_folder": "260508",
    "img_name": "point20_item-03-01.png",
    "attention": ""
  },
  {
    "topic_id": "3",
    "brand": "ヒース",
    "product_name": "プロテクトセラム",
    "price": "7,150",
    "points": "1,300",
    "is_kara": "",
    "url": "https://web.hh-online.jp/hankyu-beauty/goods/index.html?ggcd=B2490038",
    "img_folder": "260508",
    "img_name": "point20_item-03-02.png",
    "attention": ""
  },
  {
    "topic_id": "3",
    "brand": "エレクトロン",
    "product_name": "モイスチャーステムローション",
    "price": "4,950",
    "points": "900",
    "is_kara": "",
    "url": "https://web.hh-online.jp/hankyu-beauty/goods/index.html?ggcd=B2460124",
    "img_folder": "260508",
    "img_name": "point20_item-03-03.png",
    "attention": ""
  },
  {
    "topic_id": "3",
    "brand": "アスレティア",
    "product_name": "スムース ソフニング 3D マスク",
    "price": "880",
    "points": "160",
    "is_kara": "",
    "url": "https://web.hh-online.jp/hankyu-beauty/goods/index.html?ggcd=B25D0217",
    "img_folder": "260508",
    "img_name": "point20_item-03-05.png",
    "attention": ""
  },
  {
    "topic_id": "3",
    "brand": "アスレティア",
    "product_name": "コアバランス オイル",
    "price": "6,050",
    "points": "1,100",
    "is_kara": "",
    "url": "https://web.hh-online.jp/hankyu-beauty/goods/index.html?ggcd=B2010343",
    "img_folder": "260508",
    "img_name": "point20_item-03-06.png",
    "attention": ""
  },
  {
    "topic_id": "3",
    "brand": "AHRES",
    "product_name": "ポーン",
    "price": "9,900",
    "points": "1,800",
    "is_kara": "",
    "url": "https://web.hh-online.jp/hankyu-beauty/goods/index.html?ggcd=B2550235",
    "img_folder": "260508",
    "img_name": "point20_item-03-07.png",
    "attention": ""
  },
  {
    "topic_id": "3",
    "brand": "オブ･コスメティックス",
    "product_name": "ナチュラルクレイフェイスウォッシュ・F1",
    "price": "3,498",
    "points": "636",
    "is_kara": "",
    "url": "https://web.hh-online.jp/hankyu-beauty/goods/index.html?ggcd=B2160094",
    "img_folder": "260508",
    "img_name": "point20_item-03-08.png",
    "attention": ""
  },
  {
    "topic_id": "3",
    "brand": "ヘラ",
    "product_name": "コンフィー コンディショニングエッセンス",
    "price": "6,050",
    "points": "1,100",
    "is_kara": "",
    "url": "https://web.hh-online.jp/hankyu-beauty/goods/index.html?ggcd=B2620170",
    "img_folder": "260508",
    "img_name": "point20_item-03-09.png",
    "attention": ""
  },
  {
    "topic_id": "3",
    "brand": "センサイ",
    "product_name": "コンフォーティング バリアマスク",
    "price": "18,700",
    "points": "3,400",
    "is_kara": "",
    "url": "https://web.hh-online.jp/hankyu-beauty/goods/index.html?ggcd=B2280071",
    "img_folder": "260508",
    "img_name": "point20_item-03-10.png",
    "attention": ""
  },
  {
    "topic_id": "3",
    "brand": "SUQQU",
    "product_name": "アクフォンス スムース リニュー セラム[医薬部外品]",
    "price": "8,800",
    "points": "1,600",
    "is_kara": "TRUE",
    "url": "https://web.hh-online.jp/hankyu-beauty/goods/index.html?ggcd=B2520003",
    "img_folder": "260508",
    "img_name": "point20_item-03-11.png",
    "attention": ""
  },
  {
    "topic_id": "3",
    "brand": "オサジ",
    "product_name": "センシティブ スキン トライアルセット",
    "price": "4,070",
    "points": "740",
    "is_kara": "",
    "url": "https://web.hh-online.jp/hankyu-beauty/goods/index.html?ggcd=B2220134",
    "img_folder": "260508",
    "img_name": "point20_item-03-12.png",
    "attention": ""
  },
  {
    "topic_id": "3",
    "brand": "センサイ",
    "product_name": "コンフォーティング バリアエッセンス",
    "price": "18,700",
    "points": "3,400",
    "is_kara": "",
    "url": "https://web.hh-online.jp/hankyu-beauty/goods/index.html?ggcd=B2510001",
    "img_folder": "260508",
    "img_name": "point20_item-03-13.png",
    "attention": ""
  },
  {
    "topic_id": "4",
    "brand": "エレクトロン",
    "product_name": "シンクロシャンプー ファム DAMAGE REPAIR",
    "price": "3,740",
    "points": "680",
    "is_kara": "",
    "url": "https://web.hh-online.jp/hankyu-beauty/goods/index.html?ggcd=B24D0001",
    "img_folder": "260508",
    "img_name": "point20_item-04-01.png",
    "attention": ""
  },
  {
    "topic_id": "4",
    "brand": "エレクトロン",
    "product_name": "シンクロトリートメント DAMAGE REPAIR",
    "price": "3,080",
    "points": "560",
    "is_kara": "",
    "url": "https://web.hh-online.jp/hankyu-beauty/goods/index.html?ggcd=B24D0002",
    "img_folder": "260508",
    "img_name": "point20_item-04-02.png",
    "attention": ""
  },
  {
    "topic_id": "4",
    "brand": "エレクトロン",
    "product_name": "シンクロオイル(洗い流さないトリートメント)",
    "price": "3,960",
    "points": "720",
    "is_kara": "",
    "url": "https://web.hh-online.jp/hankyu-beauty/goods/index.html?ggcd=B24D0003",
    "img_folder": "260508",
    "img_name": "point20_item-04-03.png",
    "attention": ""
  },
  {
    "topic_id": "4",
    "brand": "アスレティア",
    "product_name": "リフレッシング デオドラントミスト[医薬部外品]",
    "price": "3,850",
    "points": "700",
    "is_kara": "",
    "url": "https://web.hh-online.jp/hankyu-beauty/goods/index.html?ggcd=B2230116",
    "img_folder": "260508",
    "img_name": "point20_item-04-04.png",
    "attention": ""
  },
  {
    "topic_id": "4",
    "brand": "アスレティア",
    "product_name": "リスタイリング ヘアセラム",
    "price": "4,400",
    "points": "800",
    "is_kara": "",
    "url": "https://web.hh-online.jp/hankyu-beauty/goods/index.html?ggcd=B2510124",
    "img_folder": "260508",
    "img_name": "point20_item-04-05.png",
    "attention": ""
  },
  {
    "topic_id": "4",
    "brand": "アスレティア",
    "product_name": "スキンプロテクション UVボディミスト",
    "price": "4,400",
    "points": "800",
    "is_kara": "",
    "url": "https://web.hh-online.jp/hankyu-beauty/goods/index.html?ggcd=B2520193",
    "img_folder": "260508",
    "img_name": "point20_item-04-06.png",
    "attention": ""
  },
  {
    "topic_id": "4",
    "brand": "AHRES",
    "product_name": "ハブ ア クール デイ ミスト",
    "price": "2,970",
    "points": "540",
    "is_kara": "",
    "url": "https://web.hh-online.jp/hankyu-beauty/goods/index.html?ggcd=B2440230",
    "img_folder": "260508",
    "img_name": "point20_item-04-07.png",
    "attention": ""
  },
  {
    "topic_id": "4",
    "brand": "オブ･コスメティックス",
    "product_name": "ソープオブボディ・01-G",
    "price": "4,510",
    "points": "820",
    "is_kara": "",
    "url": "https://web.hh-online.jp/hankyu-beauty/goods/index.html?ggcd=B2240052",
    "img_folder": "260508",
    "img_name": "point20_item-04-08.png",
    "attention": ""
  },
  {
    "topic_id": "4",
    "brand": "オブ･コスメティックス",
    "product_name": "ソープオブボディ・01-HS",
    "price": "4,510",
    "points": "820",
    "is_kara": "",
    "url": "https://web.hh-online.jp/hankyu-beauty/goods/index.html?ggcd=B2240053",
    "img_folder": "260508",
    "img_name": "point20_item-04-09.png",
    "attention": ""
  },
  {
    "topic_id": "4",
    "brand": "エムアイエムシー",
    "product_name": "ボディーパウダーサンスクリーン(カーミングブリーズ)",
    "price": "5,500",
    "points": "1,000",
    "is_kara": "",
    "url": "https://web.hh-online.jp/hankyu-beauty/goods/index.html?ggcd=B2530059",
    "img_folder": "260508",
    "img_name": "point20_item-04-10.png",
    "attention": ""
  },
  {
    "topic_id": "4",
    "brand": "イイスタンダード",
    "product_name": "シャンプー",
    "price": "3,630",
    "points": "660",
    "is_kara": "TRUE",
    "url": "https://web.hh-online.jp/hankyu-beauty/goods/index.html?ggcd=B19D0231",
    "img_folder": "260508",
    "img_name": "point20_item-04-11.png",
    "attention": ""
  },
  {
    "topic_id": "4",
    "brand": "センサイ",
    "product_name": "ネック アンド デコルテ エッセンス",
    "price": "11,770",
    "points": "2,140",
    "is_kara": "",
    "url": "https://web.hh-online.jp/hankyu-beauty/goods/index.html?ggcd=B2080066",
    "img_folder": "260508",
    "img_name": "point20_item-04-12.png",
    "attention": ""
  },
  {
    "topic_id": "4",
    "brand": "シロ",
    "product_name": "サボン ハンド美容液",
    "price": "3,300",
    "points": "600",
    "is_kara": "",
    "url": "https://web.hh-online.jp/hankyu-beauty/goods/index.html?ggcd=B2390382",
    "img_folder": "260508",
    "img_name": "point20_item-04-13.png",
    "attention": ""
  },
  {
    "topic_id": "4",
    "brand": "シロ",
    "product_name": "ホワイトリリー ハンド美容液",
    "price": "3,300",
    "points": "600",
    "is_kara": "",
    "url": "https://web.hh-online.jp/hankyu-beauty/goods/index.html?ggcd=B2390383",
    "img_folder": "260508",
    "img_name": "point20_item-04-14.png",
    "attention": ""
  }
]